Metadata-Version: 2.1
Name: netrunner
Version: 0.1.6
Summary: Network asyncio command runner using Scrapli
Home-page: https://github.com/rbraddev/netrunner
Keywords: network,automation,nxos,ios,iosxe,ssh,cisco
Author: Ryan Bradshaw
Author-email: ryan@rbradshaw.dev
Requires-Python: >=3.7,<4.0
Classifier: Programming Language :: Python :: 3
Classifier: Programming Language :: Python :: 3.7
Classifier: Programming Language :: Python :: 3.8
Classifier: Programming Language :: Python :: 3.9
Requires-Dist: asyncssh (>=2.7.0,<3.0.0)
Requires-Dist: genie (>=21.8,<22.0)
Requires-Dist: pyats (>=21.8,<22.0)
Requires-Dist: scrapli (>=2021.1.30,<2022.0.0)
Project-URL: Repository, https://github.com/rbraddev/netrunner
